{
  "schema_version": "medical_knowledge_database_v1",
  "artifact_type": "complaint_cds_module",
  "complaint_cds_schema_version": "complaint-cds-artifact-v1",
  "module": {
    "id": "cushings_syndrome_v1",
    "schema_version": "complaint-cds-artifact-v1",
    "label": "Cushing's Syndrome",
    "complaint_group": "adrenal_gland_disorders",
    "version": "1.0.0",
    "status": "mvp",
    "population": {
      "age_group": "adult",
      "setting": "clinician support"
    },
    "triggers": [
      "Cushing's Syndrome",
      "Cushing Syndrome",
      "cushings syndrome",
      "cushing syndrome"
    ],
    "requiredQuestions": [
      {
        "id": "question_01",
        "label": "Do you have trouble rising from a chair, climbing stairs, lifting overhead, or getting up from the floor?",
        "item_type": "history_question",
        "source": {
          "source_id": "ES_CUSHING_DX_2008",
          "source_section": "Cushing's Syndrome curated endocrine workup: required clinical questions",
          "evidence_strength": "guideline/consensus",
          "version_date": "2008",
          "last_reviewed": "2026-06-06",
          "clinical_owner": "endocrine_content_review",
          "implementation_notes": "Guideline-backed endocrine workup content curated into the local knowledge schema; schema, source, PHI, and regression tests run on 2026-06-06."
        },
        "text": "Do you have trouble rising from a chair, climbing stairs, lifting overhead, or getting up from the floor?",
        "options": [
          {
            "value": "no_orthostatic_symptom",
            "label": "No orthostatic symptom"
          },
          {
            "value": "salt_craving",
            "label": "Salt craving"
          },
          {
            "value": "lightheaded_standing",
            "label": "Lightheaded standing"
          },
          {
            "value": "fainting_near_fainting",
            "label": "Fainting/near-fainting"
          },
          {
            "value": "severe_weakness",
            "label": "Severe weakness"
          },
          {
            "value": "improves_with_fluids_salt",
            "label": "Improves with fluids/salt"
          },
          {
            "value": "other",
            "label": "Other ___"
          }
        ],
        "action": "The answer changes the leading Cushing's Syndrome pathway by refining severity, mimics, confirmatory testing, treatment safety, and follow-up timing.",
        "rationale": "Defines the patient-specific context needed to interpret endocrine tests, avoid common mimics, and choose the safest next step for Cushing's Syndrome.",
        "when_to_ask": "Ask when Cushing's Syndrome is the selected validated clinical intent or when this feature would change endocrine test interpretation, urgency, or treatment safety.",
        "diagnostic_purpose": "Defines the patient-specific context needed to interpret endocrine tests, avoid common mimics, and choose the safest next step for Cushing's Syndrome.",
        "management_implication": "The answer changes the leading Cushing's Syndrome pathway by refining severity, mimics, confirmatory testing, treatment safety, and follow-up timing.",
        "tags": [
          "adrenal_gland_disorders",
          "cushings_syndrome",
          "proximal",
          "weakness"
        ],
        "source_seed": "Proximal weakness, easy bruising, purple striae, fractures, infections."
      },
      {
        "id": "question_02",
        "label": "Any measured fever, rigors, hypothermia, or toxic appearance suggesting infection as a precipitant or mimic?",
        "item_type": "history_question",
        "source": {
          "source_id": "ES_CUSHING_DX_2008",
          "source_section": "Cushing's Syndrome curated endocrine workup: required clinical questions",
          "evidence_strength": "guideline/consensus",
          "version_date": "2008",
          "last_reviewed": "2026-06-06",
          "clinical_owner": "endocrine_content_review",
          "implementation_notes": "Guideline-backed endocrine workup content curated into the local knowledge schema; schema, source, PHI, and regression tests run on 2026-06-06."
        },
        "text": "Any measured fever, rigors, hypothermia, or toxic appearance suggesting infection as a precipitant or mimic?",
        "options": [
          {
            "value": "no_measured_fever",
            "label": "No measured fever"
          },
          {
            "value": "less_than_39_c",
            "label": "Less than 39 C"
          },
          {
            "value": "39_c_or_higher",
            "label": "39 C or higher"
          },
          {
            "value": "chills_or_rigors",
            "label": "Chills or rigors"
          },
          {
            "value": "hypothermia_toxic_appearance",
            "label": "Hypothermia/toxic appearance"
          },
          {
            "value": "unknown",
            "label": "Unknown"
          },
          {
            "value": "other",
            "label": "Other ___"
          }
        ],
        "action": "A positive answer changes adrenal-crisis risk, stress-dose steroid urgency, volume strategy, electrolyte/glucose testing, infection search, and monitored-care threshold for Cushing's Syndrome.",
        "rationale": "Defines the patient-specific context needed to interpret endocrine tests, avoid common mimics, and choose the safest next step for Cushing's Syndrome.",
        "when_to_ask": "Ask when Cushing's Syndrome is the selected validated clinical intent or when this feature would change endocrine test interpretation, urgency, or treatment safety.",
        "diagnostic_purpose": "Defines the patient-specific context needed to interpret endocrine tests, avoid common mimics, and choose the safest next step for Cushing's Syndrome.",
        "management_implication": "A positive answer changes adrenal-crisis risk, stress-dose steroid urgency, volume strategy, electrolyte/glucose testing, infection search, and monitored-care threshold for Cushing's Syndrome.",
        "tags": [
          "adrenal_gland_disorders",
          "cushings_syndrome",
          "fever",
          "rigors"
        ],
        "source_seed": "Proximal weakness, easy bruising, purple striae, fractures, infections."
      },
      {
        "id": "question_03",
        "label": "Any cough, sputum, pleuritic pain, dyspnea, hypoxemia, or focal chest symptoms suggesting pneumonia or respiratory infection?",
        "item_type": "history_question",
        "source": {
          "source_id": "ES_CUSHING_DX_2008",
          "source_section": "Cushing's Syndrome curated endocrine workup: required clinical questions",
          "evidence_strength": "guideline/consensus",
          "version_date": "2008",
          "last_reviewed": "2026-06-06",
          "clinical_owner": "endocrine_content_review",
          "implementation_notes": "Guideline-backed endocrine workup content curated into the local knowledge schema; schema, source, PHI, and regression tests run on 2026-06-06."
        },
        "text": "Any cough, sputum, pleuritic pain, dyspnea, hypoxemia, or focal chest symptoms suggesting pneumonia or respiratory infection?",
        "options": [
          {
            "value": "no_respiratory_symptoms",
            "label": "No respiratory symptoms"
          },
          {
            "value": "cough",
            "label": "Cough"
          },
          {
            "value": "sputum",
            "label": "Sputum"
          },
          {
            "value": "shortness_of_breath",
            "label": "Shortness of breath"
          },
          {
            "value": "pleuritic_pain",
            "label": "Pleuritic pain"
          },
          {
            "value": "hypoxemia_or_oxygen_need",
            "label": "Hypoxemia or oxygen need"
          },
          {
            "value": "other",
            "label": "Other ___"
          }
        ],
        "action": "A positive answer changes adrenal-crisis risk, stress-dose steroid urgency, volume strategy, electrolyte/glucose testing, infection search, and monitored-care threshold for Cushing's Syndrome.",
        "rationale": "Defines symptom severity, tempo, complications, and whether Cushing's Syndrome needs urgent evaluation today.",
        "when_to_ask": "Ask when Cushing's Syndrome is the selected validated clinical intent or when this feature would change endocrine test interpretation, urgency, or treatment safety.",
        "diagnostic_purpose": "Defines symptom severity, tempo, complications, and whether Cushing's Syndrome needs urgent evaluation today.",
        "management_implication": "A positive answer changes adrenal-crisis risk, stress-dose steroid urgency, volume strategy, electrolyte/glucose testing, infection search, and monitored-care threshold for Cushing's Syndrome.",
        "tags": [
          "adrenal_gland_disorders",
          "cushings_syndrome",
          "respiratory",
          "infection"
        ],
        "source_seed": "Proximal weakness, easy bruising, purple striae, fractures, infections."
      },
      {
        "id": "question_04",
        "label": "Any dysuria, urinary frequency or urgency, suprapubic pain, hematuria, or flank pain suggesting UTI or pyelonephritis?",
        "item_type": "history_question",
        "source": {
          "source_id": "ES_CUSHING_DX_2008",
          "source_section": "Cushing's Syndrome curated endocrine workup: required clinical questions",
          "evidence_strength": "guideline/consensus",
          "version_date": "2008",
          "last_reviewed": "2026-06-06",
          "clinical_owner": "endocrine_content_review",
          "implementation_notes": "Guideline-backed endocrine workup content curated into the local knowledge schema; schema, source, PHI, and regression tests run on 2026-06-06."
        },
        "text": "Any dysuria, urinary frequency or urgency, suprapubic pain, hematuria, or flank pain suggesting UTI or pyelonephritis?",
        "options": [
          {
            "value": "no_urinary_symptoms",
            "label": "No urinary symptoms"
          },
          {
            "value": "dysuria",
            "label": "Dysuria"
          },
          {
            "value": "frequency_or_urgency",
            "label": "Frequency or urgency"
          },
          {
            "value": "suprapubic_pain",
            "label": "Suprapubic pain"
          },
          {
            "value": "hematuria",
            "label": "Hematuria"
          },
          {
            "value": "flank_pain",
            "label": "Flank pain"
          },
          {
            "value": "reduced_urine",
            "label": "Reduced urine"
          },
          {
            "value": "other",
            "label": "Other ___"
          }
        ],
        "action": "The answer changes the leading Cushing's Syndrome pathway by refining severity, mimics, confirmatory testing, treatment safety, and follow-up timing.",
        "rationale": "Defines symptom severity, tempo, complications, and whether Cushing's Syndrome needs urgent evaluation today.",
        "when_to_ask": "Ask when Cushing's Syndrome is the selected validated clinical intent or when this feature would change endocrine test interpretation, urgency, or treatment safety.",
        "diagnostic_purpose": "Defines symptom severity, tempo, complications, and whether Cushing's Syndrome needs urgent evaluation today.",
        "management_implication": "The answer changes the leading Cushing's Syndrome pathway by refining severity, mimics, confirmatory testing, treatment safety, and follow-up timing.",
        "tags": [
          "adrenal_gland_disorders",
          "cushings_syndrome",
          "urinary",
          "flank",
          "infection"
        ],
        "source_seed": "Proximal weakness, easy bruising, purple striae, fractures, infections."
      },
      {
        "id": "question_05",
        "label": "Any wound, skin redness, drainage, tenderness, indwelling line/device, or procedure-site concern suggesting infection?",
        "item_type": "history_question",
        "source": {
          "source_id": "ES_CUSHING_DX_2008",
          "source_section": "Cushing's Syndrome curated endocrine workup: required clinical questions",
          "evidence_strength": "guideline/consensus",
          "version_date": "2008",
          "last_reviewed": "2026-06-06",
          "clinical_owner": "endocrine_content_review",
          "implementation_notes": "Guideline-backed endocrine workup content curated into the local knowledge schema; schema, source, PHI, and regression tests run on 2026-06-06."
        },
        "text": "Any wound, skin redness, drainage, tenderness, indwelling line/device, or procedure-site concern suggesting infection?",
        "options": [
          {
            "value": "no_skin_or_line_concern",
            "label": "No skin or line concern"
          },
          {
            "value": "redness",
            "label": "Redness"
          },
          {
            "value": "drainage",
            "label": "Drainage"
          },
          {
            "value": "wound_or_ulcer",
            "label": "Wound or ulcer"
          },
          {
            "value": "line_device_concern",
            "label": "Line/device concern"
          },
          {
            "value": "procedure_site_concern",
            "label": "Procedure-site concern"
          },
          {
            "value": "other",
            "label": "Other ___"
          }
        ],
        "action": "A positive answer changes adrenal-crisis risk, stress-dose steroid urgency, volume strategy, electrolyte/glucose testing, infection search, and monitored-care threshold for Cushing's Syndrome.",
        "rationale": "Identifies exposures, physiologic states, or treatment changes that can explain abnormal results or make Cushing's Syndrome therapy unsafe.",
        "when_to_ask": "Ask when Cushing's Syndrome is the selected validated clinical intent or when this feature would change endocrine test interpretation, urgency, or treatment safety.",
        "diagnostic_purpose": "Identifies exposures, physiologic states, or treatment changes that can explain abnormal results or make Cushing's Syndrome therapy unsafe.",
        "management_implication": "A positive answer changes adrenal-crisis risk, stress-dose steroid urgency, volume strategy, electrolyte/glucose testing, infection search, and monitored-care threshold for Cushing's Syndrome.",
        "tags": [
          "adrenal_gland_disorders",
          "cushings_syndrome",
          "skin",
          "wound",
          "line",
          "procedure",
          "site",
          "infection"
        ],
        "source_seed": "Proximal weakness, easy bruising, purple striae, fractures, infections."
      },
      {
        "id": "question_06",
        "label": "Any new, worsening, resistant, or treatment-limiting hypertension or diabetes that changes endocrine severity, complication screening, or medication choice?",
        "item_type": "history_question",
        "source": {
          "source_id": "ES_CUSHING_DX_2008",
          "source_section": "Cushing's Syndrome curated endocrine workup: required clinical questions",
          "evidence_strength": "guideline/consensus",
          "version_date": "2008",
          "last_reviewed": "2026-06-06",
          "clinical_owner": "endocrine_content_review",
          "implementation_notes": "Guideline-backed endocrine workup content curated into the local knowledge schema; schema, source, PHI, and regression tests run on 2026-06-06."
        },
        "text": "Any new, worsening, resistant, or treatment-limiting hypertension or diabetes that changes endocrine severity, complication screening, or medication choice?",
        "options": [
          {
            "value": "no_relevant_exposure",
            "label": "No relevant exposure"
          },
          {
            "value": "medication_change",
            "label": "Medication change"
          },
          {
            "value": "supplement_use",
            "label": "Supplement use"
          },
          {
            "value": "missed_doses",
            "label": "Missed doses"
          },
          {
            "value": "steroid_or_hormone_exposure",
            "label": "Steroid or hormone exposure"
          },
          {
            "value": "biotin",
            "label": "Biotin"
          },
          {
            "value": "iodine_contrast_exposure",
            "label": "Iodine/contrast exposure"
          },
          {
            "value": "other",
            "label": "Other ___"
          }
        ],
        "action": "The answer changes cardiometabolic risk stratification, prevention intensity, complication screening, and follow-up interval for Cushing's Syndrome.",
        "rationale": "Identifies exposures, physiologic states, or treatment changes that can explain abnormal results or make Cushing's Syndrome therapy unsafe.",
        "when_to_ask": "Ask when Cushing's Syndrome is the selected validated clinical intent or when this feature would change endocrine test interpretation, urgency, or treatment safety.",
        "diagnostic_purpose": "Identifies exposures, physiologic states, or treatment changes that can explain abnormal results or make Cushing's Syndrome therapy unsafe.",
        "management_implication": "The answer changes cardiometabolic risk stratification, prevention intensity, complication screening, and follow-up interval for Cushing's Syndrome.",
        "tags": [
          "adrenal_gland_disorders",
          "cushings_syndrome",
          "hypertension"
        ],
        "source_seed": "Hypertension, diabetes, mood/sleep changes."
      },
      {
        "id": "question_07",
        "label": "Do you feel lightheaded when standing, faint, unusually weak, or better after fluids or salt?",
        "item_type": "history_question",
        "source": {
          "source_id": "ES_CUSHING_DX_2008",
          "source_section": "Cushing's Syndrome curated endocrine workup: required clinical questions",
          "evidence_strength": "guideline/consensus",
          "version_date": "2008",
          "last_reviewed": "2026-06-06",
          "clinical_owner": "endocrine_content_review",
          "implementation_notes": "Guideline-backed endocrine workup content curated into the local knowledge schema; schema, source, PHI, and regression tests run on 2026-06-06."
        },
        "text": "Do you feel lightheaded when standing, faint, unusually weak, or better after fluids or salt?",
        "options": [
          {
            "value": "no_orthostatic_symptom",
            "label": "No orthostatic symptom"
          },
          {
            "value": "salt_craving",
            "label": "Salt craving"
          },
          {
            "value": "lightheaded_standing",
            "label": "Lightheaded standing"
          },
          {
            "value": "fainting_near_fainting",
            "label": "Fainting/near-fainting"
          },
          {
            "value": "severe_weakness",
            "label": "Severe weakness"
          },
          {
            "value": "improves_with_fluids_salt",
            "label": "Improves with fluids/salt"
          },
          {
            "value": "other",
            "label": "Other ___"
          }
        ],
        "action": "A positive answer changes adrenal-crisis risk, stress-dose steroid urgency, volume strategy, electrolyte/glucose testing, infection search, and monitored-care threshold for Cushing's Syndrome.",
        "rationale": "Defines the patient-specific context needed to interpret endocrine tests, avoid common mimics, and choose the safest next step for Cushing's Syndrome.",
        "when_to_ask": "Ask when Cushing's Syndrome is the selected validated clinical intent or when this feature would change endocrine test interpretation, urgency, or treatment safety.",
        "diagnostic_purpose": "Defines the patient-specific context needed to interpret endocrine tests, avoid common mimics, and choose the safest next step for Cushing's Syndrome.",
        "management_implication": "A positive answer changes adrenal-crisis risk, stress-dose steroid urgency, volume strategy, electrolyte/glucose testing, infection search, and monitored-care threshold for Cushing's Syndrome.",
        "tags": [
          "adrenal_gland_disorders",
          "cushings_syndrome",
          "orthostasis"
        ],
        "source_seed": "Ask about orthostasis, salt craving, weight loss, nausea/vomiting, abdominal pain, headaches/sweats/palpitations, resistant hypertension, hypokalemia, steroid exposure, and adrenal incidentaloma."
      },
      {
        "id": "question_08",
        "label": "Have you had new salt craving, dizziness on standing, low blood pressure, vomiting, abdominal pain, or unusual skin darkening?",
        "item_type": "history_question",
        "source": {
          "source_id": "ES_CUSHING_DX_2008",
          "source_section": "Cushing's Syndrome curated endocrine workup: required clinical questions",
          "evidence_strength": "guideline/consensus",
          "version_date": "2008",
          "last_reviewed": "2026-06-06",
          "clinical_owner": "endocrine_content_review",
          "implementation_notes": "Guideline-backed endocrine workup content curated into the local knowledge schema; schema, source, PHI, and regression tests run on 2026-06-06."
        },
        "text": "Have you had new salt craving, dizziness on standing, low blood pressure, vomiting, abdominal pain, or unusual skin darkening?",
        "options": [
          {
            "value": "no_gi_volume_symptom",
            "label": "No GI/volume symptom"
          },
          {
            "value": "vomiting",
            "label": "Vomiting"
          },
          {
            "value": "nausea",
            "label": "Nausea"
          },
          {
            "value": "abdominal_pain",
            "label": "Abdominal pain"
          },
          {
            "value": "poor_intake",
            "label": "Poor intake"
          },
          {
            "value": "cannot_keep_fluids_meds_down",
            "label": "Cannot keep fluids/meds down"
          },
          {
            "value": "other",
            "label": "Other ___"
          }
        ],
        "action": "A positive answer changes adrenal-crisis risk, stress-dose steroid urgency, volume strategy, electrolyte/glucose testing, infection search, and monitored-care threshold for Cushing's Syndrome.",
        "rationale": "Defines symptom severity, tempo, complications, and whether Cushing's Syndrome needs urgent evaluation today.",
        "when_to_ask": "Ask when Cushing's Syndrome is the selected validated clinical intent or when this feature would change endocrine test interpretation, urgency, or treatment safety.",
        "diagnostic_purpose": "Defines symptom severity, tempo, complications, and whether Cushing's Syndrome needs urgent evaluation today.",
        "management_implication": "A positive answer changes adrenal-crisis risk, stress-dose steroid urgency, volume strategy, electrolyte/glucose testing, infection search, and monitored-care threshold for Cushing's Syndrome.",
        "tags": [
          "adrenal_gland_disorders",
          "cushings_syndrome",
          "salt",
          "craving"
        ],
        "source_seed": "Ask about orthostasis, salt craving, weight loss, nausea/vomiting, abdominal pain, headaches/sweats/palpitations, resistant hypertension, hypokalemia, steroid exposure, and adrenal incidentaloma."
      },
      {
        "id": "question_09",
        "label": "How has weight changed from baseline, and was the change intentional or associated with appetite, fluid status, or systemic symptoms?",
        "item_type": "history_question",
        "source": {
          "source_id": "ES_CUSHING_DX_2008",
          "source_section": "Cushing's Syndrome curated endocrine workup: required clinical questions",
          "evidence_strength": "guideline/consensus",
          "version_date": "2008",
          "last_reviewed": "2026-06-06",
          "clinical_owner": "endocrine_content_review",
          "implementation_notes": "Guideline-backed endocrine workup content curated into the local knowledge schema; schema, source, PHI, and regression tests run on 2026-06-06."
        },
        "text": "How has weight changed from baseline, and was the change intentional or associated with appetite, fluid status, or systemic symptoms?",
        "options": [
          {
            "value": "today_or_acute_onset",
            "label": "Today or acute onset"
          },
          {
            "value": "days",
            "label": "Days"
          },
          {
            "value": "weeks_to_months",
            "label": "Weeks to months"
          },
          {
            "value": "chronic_or_baseline",
            "label": "Chronic or baseline"
          },
          {
            "value": "worse_today",
            "label": "Worse today"
          },
          {
            "value": "unknown",
            "label": "Unknown"
          },
          {
            "value": "other",
            "label": "Other ___"
          }
        ],
        "action": "The answer changes cardiometabolic risk stratification, prevention intensity, complication screening, and follow-up interval for Cushing's Syndrome.",
        "rationale": "Defines symptom severity, tempo, complications, and whether Cushing's Syndrome needs urgent evaluation today.",
        "when_to_ask": "Ask when Cushing's Syndrome is the selected validated clinical intent or when this feature would change endocrine test interpretation, urgency, or treatment safety.",
        "diagnostic_purpose": "Defines symptom severity, tempo, complications, and whether Cushing's Syndrome needs urgent evaluation today.",
        "management_implication": "The answer changes cardiometabolic risk stratification, prevention intensity, complication screening, and follow-up interval for Cushing's Syndrome.",
        "tags": [
          "adrenal_gland_disorders",
          "cushings_syndrome",
          "weight",
          "loss"
        ],
        "source_seed": "Ask about orthostasis, salt craving, weight loss, nausea/vomiting, abdominal pain, headaches/sweats/palpitations, resistant hypertension, hypokalemia, steroid exposure, and adrenal incidentaloma."
      },
      {
        "id": "question_10",
        "label": "Any new headache, peripheral vision loss, double vision, eye movement pain, sudden severe headache, nausea, or pituitary surgery/radiation history?",
        "item_type": "history_question",
        "source": {
          "source_id": "ES_CUSHING_DX_2008",
          "source_section": "Cushing's Syndrome curated endocrine workup: required clinical questions",
          "evidence_strength": "guideline/consensus",
          "version_date": "2008",
          "last_reviewed": "2026-06-06",
          "clinical_owner": "endocrine_content_review",
          "implementation_notes": "Guideline-backed endocrine workup content curated into the local knowledge schema; schema, source, PHI, and regression tests run on 2026-06-06."
        },
        "text": "Any new headache, peripheral vision loss, double vision, eye movement pain, sudden severe headache, nausea, or pituitary surgery/radiation history?",
        "options": [
          {
            "value": "no_gi_volume_symptom",
            "label": "No GI/volume symptom"
          },
          {
            "value": "vomiting",
            "label": "Vomiting"
          },
          {
            "value": "nausea",
            "label": "Nausea"
          },
          {
            "value": "abdominal_pain",
            "label": "Abdominal pain"
          },
          {
            "value": "poor_intake",
            "label": "Poor intake"
          },
          {
            "value": "cannot_keep_fluids_meds_down",
            "label": "Cannot keep fluids/meds down"
          },
          {
            "value": "other",
            "label": "Other ___"
          }
        ],
        "action": "The answer changes central endocrine localization, pituitary MRI or visual-field review, axis testing, and neurosurgical or ophthalmology escalation for Cushing's Syndrome.",
        "rationale": "Defines symptom severity, tempo, complications, and whether Cushing's Syndrome needs urgent evaluation today.",
        "when_to_ask": "Ask when Cushing's Syndrome is the selected validated clinical intent or when this feature would change endocrine test interpretation, urgency, or treatment safety.",
        "diagnostic_purpose": "Defines symptom severity, tempo, complications, and whether Cushing's Syndrome needs urgent evaluation today.",
        "management_implication": "The answer changes central endocrine localization, pituitary MRI or visual-field review, axis testing, and neurosurgical or ophthalmology escalation for Cushing's Syndrome.",
        "tags": [
          "adrenal_gland_disorders",
          "cushings_syndrome",
          "adrenal",
          "pituitary",
          "surgery"
        ],
        "source_seed": "Clarify exogenous glucocorticoids including injections/creams/inhalers, adrenal/pituitary surgery, autoimmune disease, MEN/VHL/NF1/SDHx history, pregnancy, and acute infection."
      }
    ],
    "conditionalQuestions": [
      {
        "id": "question_01",
        "label": "Any abdominal pain, nausea/vomiting, poor intake, salt craving, orthostasis, weight loss, or new skin/oral hyperpigmentation suggesting adrenal insufficiency or crisis physiology?",
        "item_type": "history_question",
        "source": {
          "source_id": "ES_CUSHING_DX_2008",
          "source_section": "Cushing's Syndrome curated endocrine workup: conditional clinical questions",
          "evidence_strength": "guideline/consensus",
          "version_date": "2008",
          "last_reviewed": "2026-06-06",
          "clinical_owner": "endocrine_content_review",
          "implementation_notes": "Guideline-backed endocrine workup content curated into the local knowledge schema; schema, source, PHI, and regression tests run on 2026-06-06."
        },
        "text": "Any abdominal pain, nausea/vomiting, poor intake, salt craving, orthostasis, weight loss, or new skin/oral hyperpigmentation suggesting adrenal insufficiency or crisis physiology?",
        "options": [
          {
            "value": "no_gi_volume_symptom",
            "label": "No GI/volume symptom"
          },
          {
            "value": "vomiting",
            "label": "Vomiting"
          },
          {
            "value": "nausea",
            "label": "Nausea"
          },
          {
            "value": "abdominal_pain",
            "label": "Abdominal pain"
          },
          {
            "value": "poor_intake",
            "label": "Poor intake"
          },
          {
            "value": "cannot_keep_fluids_meds_down",
            "label": "Cannot keep fluids/meds down"
          },
          {
            "value": "other",
            "label": "Other ___"
          }
        ],
        "action": "Ask when the history or modifiers support weight, appetite, fluid, or systemic-symptom change; adrenal-crisis or volume-depletion symptoms. A positive answer changes adrenal-crisis risk, stress-dose steroid urgency, volume strategy, electrolyte/glucose testing, infection search, and monitored-care threshold for Cushing's Syndrome.",
        "rationale": "Defines symptom severity, tempo, complications, and whether Cushing's Syndrome needs urgent evaluation today.",
        "when_to_ask": "Ask when patient context includes weight, appetite, fluid, or systemic-symptom change; adrenal-crisis or volume-depletion symptoms.",
        "diagnostic_purpose": "Defines symptom severity, tempo, complications, and whether Cushing's Syndrome needs urgent evaluation today.",
        "management_implication": "A positive answer changes adrenal-crisis risk, stress-dose steroid urgency, volume strategy, electrolyte/glucose testing, infection search, and monitored-care threshold for Cushing's Syndrome.",
        "tags": [
          "adrenal_gland_disorders",
          "cushings_syndrome",
          "abdominal",
          "pain"
        ],
        "source_seed": "Ask about orthostasis, salt craving, weight loss, nausea/vomiting, abdominal pain, headaches/sweats/palpitations, resistant hypertension, hypokalemia, steroid exposure, and adrenal incidentaloma.",
        "when": {
          "termsAny": [
            "abdominal",
            "pain",
            "nausea",
            "vomiting",
            "poor",
            "intake",
            "salt",
            "craving",
            "orthostasis",
            "weight"
          ]
        }
      }
    ],
    "requiredExam": [
      {
        "id": "exam_01",
        "label": "Inspect skin for bruising",
        "item_type": "physical_exam_maneuver",
        "source": {
          "source_id": "ES_CUSHING_DX_2008",
          "source_section": "Cushing's Syndrome curated endocrine workup: required bedside maneuver",
          "evidence_strength": "guideline/consensus",
          "version_date": "2008",
          "last_reviewed": "2026-06-06",
          "clinical_owner": "endocrine_content_review",
          "implementation_notes": "Guideline-backed endocrine workup content curated into the local knowledge schema; schema, source, PHI, and regression tests run on 2026-06-06."
        },
        "action": "Use this maneuver to evaluate hypercortisolism, Cushing phenotype, or glucocorticoid excess pattern. Easy bruising supports hypercortisolism phenotype and changes testing threshold.",
        "rationale": "Checks complications or precipitating illness that change treatment intensity, prevention, and disposition for Cushing's Syndrome.",
        "technique": "Inspect exposed skin and body habitus for easy bruising, wide purple striae, supraclavicular fullness, and related Cushingoid features.",
        "findings_options": [
          "Absent",
          "Present",
          "Marked",
          "Unable to assess"
        ],
        "when_to_perform": "When Cushing syndrome or glucocorticoid excess is possible",
        "diagnostic_target": "hypercortisolism, Cushing phenotype, or glucocorticoid excess pattern",
        "LR_plus": "n/a",
        "LR_minus": "n/a",
        "likelihood_ratio_note": "No maneuver-specific LR+/LR- is available in the local validated source metadata; treat this bedside finding as supportive and interpret it with the cited guideline, diagnostic tests, and patient context.",
        "management_change": "Easy bruising supports hypercortisolism phenotype and changes testing threshold.",
        "difficulty": "easy",
        "time_burden_minutes": 1,
        "equipment_needed": "none",
        "patient_cooperation_required": "low",
        "limitations": "Inspect skin for bruising is supportive for Cushing's Syndrome, not diagnostic by itself; reliability can be reduced by pain, positioning, acute illness, cooperation, body habitus, baseline disability, and examiner technique.",
        "tags": [
          "adrenal_gland_disorders",
          "cushings_syndrome",
          "inspect",
          "skin",
          "bruising"
        ]
      },
      {
        "id": "exam_02",
        "label": "Test chair-rise strength",
        "item_type": "physical_exam_maneuver",
        "source": {
          "source_id": "ES_CUSHING_DX_2008",
          "source_section": "Cushing's Syndrome curated endocrine workup: required bedside maneuver",
          "evidence_strength": "guideline/consensus",
          "version_date": "2008",
          "last_reviewed": "2026-06-06",
          "clinical_owner": "endocrine_content_review",
          "implementation_notes": "Guideline-backed endocrine workup content curated into the local knowledge schema; schema, source, PHI, and regression tests run on 2026-06-06."
        },
        "action": "Use this maneuver to evaluate hypercortisolism-related proximal myopathy and functional severity. Proximal weakness changes Cushing severity assessment and urgency of endocrine evaluation.",
        "rationale": "Targets hypercortisolism-related proximal myopathy and functional severity; positive, negative, or unable-to-assess findings guide escalation, diagnostic testing, treatment safety, or specialty planning for Cushing's Syndrome.",
        "technique": "Ask the patient to rise from a chair without using arms if safe, observing proximal strength and need for assistance.",
        "findings_options": [
          "Normal strength",
          "Mild weakness",
          "Needs arms/assistance",
          "Unable/unsafe to assess"
        ],
        "when_to_perform": "When Cushing syndrome or glucocorticoid myopathy is possible",
        "diagnostic_target": "hypercortisolism-related proximal myopathy and functional severity",
        "LR_plus": "n/a",
        "LR_minus": "n/a",
        "likelihood_ratio_note": "No maneuver-specific LR+/LR- is available in the local validated source metadata; treat this bedside finding as supportive and interpret it with the cited guideline, diagnostic tests, and patient context.",
        "management_change": "Proximal weakness changes Cushing severity assessment and urgency of endocrine evaluation.",
        "difficulty": "easy",
        "time_burden_minutes": 1,
        "equipment_needed": "none",
        "patient_cooperation_required": "low",
        "limitations": "Test chair-rise strength is supportive for Cushing's Syndrome, not diagnostic by itself; reliability can be reduced by pain, positioning, acute illness, cooperation, body habitus, baseline disability, and examiner technique.",
        "tags": [
          "adrenal_gland_disorders",
          "cushings_syndrome",
          "test",
          "chair",
          "rise",
          "strength"
        ]
      },
      {
        "id": "exam_03",
        "label": "Inspect abdomen for purple striae",
        "item_type": "physical_exam_maneuver",
        "source": {
          "source_id": "ES_CUSHING_DX_2008",
          "source_section": "Cushing's Syndrome curated endocrine workup: required bedside maneuver",
          "evidence_strength": "guideline/consensus",
          "version_date": "2008",
          "last_reviewed": "2026-06-06",
          "clinical_owner": "endocrine_content_review",
          "implementation_notes": "Guideline-backed endocrine workup content curated into the local knowledge schema; schema, source, PHI, and regression tests run on 2026-06-06."
        },
        "action": "Use this maneuver to evaluate hypercortisolism, Cushing phenotype, or glucocorticoid excess pattern. Wide purple striae increase clinical suspicion and justify hypercortisolism testing.",
        "rationale": "Targets hypercortisolism, Cushing phenotype, or glucocorticoid excess pattern; positive, negative, or unable-to-assess findings guide escalation, diagnostic testing, treatment safety, or specialty planning for Cushing's Syndrome.",
        "technique": "Inspect exposed skin and body habitus for easy bruising, wide purple striae, supraclavicular fullness, and related Cushingoid features.",
        "findings_options": [
          "Absent",
          "Present",
          "Marked",
          "Unable to assess"
        ],
        "when_to_perform": "When Cushing syndrome is suspected",
        "diagnostic_target": "hypercortisolism, Cushing phenotype, or glucocorticoid excess pattern",
        "LR_plus": "n/a",
        "LR_minus": "n/a",
        "likelihood_ratio_note": "No maneuver-specific LR+/LR- is available in the local validated source metadata; treat this bedside finding as supportive and interpret it with the cited guideline, diagnostic tests, and patient context.",
        "management_change": "Wide purple striae increase clinical suspicion and justify hypercortisolism testing.",
        "difficulty": "easy",
        "time_burden_minutes": 1,
        "equipment_needed": "none",
        "patient_cooperation_required": "low",
        "limitations": "Inspect abdomen for purple striae is supportive for Cushing's Syndrome, not diagnostic by itself; reliability can be reduced by pain, positioning, acute illness, cooperation, body habitus, baseline disability, and examiner technique.",
        "tags": [
          "adrenal_gland_disorders",
          "cushings_syndrome",
          "inspect",
          "abdomen",
          "purple",
          "striae"
        ]
      },
      {
        "id": "exam_04",
        "label": "Inspect supraclavicular fullness",
        "item_type": "physical_exam_maneuver",
        "source": {
          "source_id": "ES_CUSHING_DX_2008",
          "source_section": "Cushing's Syndrome curated endocrine workup: required bedside maneuver",
          "evidence_strength": "guideline/consensus",
          "version_date": "2008",
          "last_reviewed": "2026-06-06",
          "clinical_owner": "endocrine_content_review",
          "implementation_notes": "Guideline-backed endocrine workup content curated into the local knowledge schema; schema, source, PHI, and regression tests run on 2026-06-06."
        },
        "action": "Use this maneuver to evaluate hypercortisolism, Cushing phenotype, or glucocorticoid excess pattern. Supraclavicular fat distribution supports Cushing phenotype and affects pretest probability.",
        "rationale": "Targets hypercortisolism, Cushing phenotype, or glucocorticoid excess pattern; positive, negative, or unable-to-assess findings guide escalation, diagnostic testing, treatment safety, or specialty planning for Cushing's Syndrome.",
        "technique": "Inspect exposed skin and body habitus for easy bruising, wide purple striae, supraclavicular fullness, and related Cushingoid features.",
        "findings_options": [
          "Absent",
          "Present",
          "Marked",
          "Unable to assess"
        ],
        "when_to_perform": "When Cushing syndrome is suspected",
        "diagnostic_target": "hypercortisolism, Cushing phenotype, or glucocorticoid excess pattern",
        "LR_plus": "n/a",
        "LR_minus": "n/a",
        "likelihood_ratio_note": "No maneuver-specific LR+/LR- is available in the local validated source metadata; treat this bedside finding as supportive and interpret it with the cited guideline, diagnostic tests, and patient context.",
        "management_change": "Supraclavicular fat distribution supports Cushing phenotype and affects pretest probability.",
        "difficulty": "easy",
        "time_burden_minutes": 1,
        "equipment_needed": "none",
        "patient_cooperation_required": "low",
        "limitations": "Inspect supraclavicular fullness is supportive for Cushing's Syndrome, not diagnostic by itself; reliability can be reduced by pain, positioning, acute illness, cooperation, body habitus, baseline disability, and examiner technique.",
        "tags": [
          "adrenal_gland_disorders",
          "cushings_syndrome",
          "inspect",
          "supraclavicular",
          "fullness"
        ]
      },
      {
        "id": "safety_check_01",
        "label": "Measure blood pressure",
        "item_type": "physical_exam_maneuver",
        "source": {
          "source_id": "ES_CUSHING_DX_2008",
          "source_section": "Cushing's Syndrome curated endocrine workup: basic bedside data and safety checks",
          "evidence_strength": "guideline/consensus",
          "version_date": "2008",
          "last_reviewed": "2026-06-06",
          "clinical_owner": "endocrine_content_review",
          "implementation_notes": "Guideline-backed endocrine workup content curated into the local knowledge schema; schema, source, PHI, and regression tests run on 2026-06-06."
        },
        "action": "Check and document as baseline bedside data for this workup. Hypotension or severe hypertension changes acuity, medication safety, fluid strategy, and escalation.",
        "when_to_perform": "Perform when Cushing's Syndrome is the selected validated workup and the maneuver is clinically safe and relevant at bedside.",
        "findings_options": [
          "___/___ mmHg",
          "Hypotensive",
          "Severe hypertension",
          "Orthostatic concern",
          "Not available"
        ],
        "diagnostic_target": "hemodynamic safety, hypertension or hypotension severity, and medication or fluid-safety context",
        "LR_plus": "n/a",
        "LR_minus": "n/a",
        "management_change": "Hypotension or severe hypertension changes acuity, medication safety, fluid strategy, and escalation.",
        "difficulty": "easy",
        "time_burden_minutes": 1,
        "equipment_needed": "blood pressure cuff",
        "patient_cooperation_required": "low",
        "limitations": "Single readings can be affected by cuff size, positioning, pain, anxiety, arrhythmia, recent activity, and medications; repeat or compare with baseline when results change management.",
        "likelihood_ratio_note": "Likelihood ratios are not applicable to routine bedside safety data; use this item to assess acuity, monitoring needs, and management safety rather than diagnostic probability.",
        "tags": [
          "adrenal_gland_disorders",
          "cushings_syndrome",
          "measure",
          "blood",
          "pressure"
        ],
        "technique": "Measure blood pressure using an appropriately sized cuff after a brief rest period, seated or supine as clinically appropriate.",
        "rationale": "Targets hemodynamic safety, hypertension or hypotension severity, and medication or fluid-safety context; positive, negative, or unable-to-assess findings guide escalation, diagnostic testing, treatment safety, or specialty planning for Cushing's Syndrome."
      },
      {
        "id": "safety_check_02",
        "label": "Measure heart rate",
        "item_type": "physical_exam_maneuver",
        "source": {
          "source_id": "ES_CUSHING_DX_2008",
          "source_section": "Cushing's Syndrome curated endocrine workup: basic bedside data and safety checks",
          "evidence_strength": "guideline/consensus",
          "version_date": "2008",
          "last_reviewed": "2026-06-06",
          "clinical_owner": "endocrine_content_review",
          "implementation_notes": "Guideline-backed endocrine workup content curated into the local knowledge schema; schema, source, PHI, and regression tests run on 2026-06-06."
        },
        "action": "Check and document as baseline bedside data for this workup. Tachycardia, bradycardia, or irregular rhythm changes acuity, ECG need, and treatment urgency.",
        "when_to_perform": "Perform when Cushing's Syndrome is the selected validated workup and the maneuver is clinically safe and relevant at bedside.",
        "findings_options": [
          "___ bpm regular",
          "Tachycardic",
          "Bradycardic",
          "Irregular",
          "Not available"
        ],
        "diagnostic_target": "tachycardia, bradycardia, irregular rhythm, or acute physiologic stress",
        "LR_plus": "n/a",
        "LR_minus": "n/a",
        "management_change": "Tachycardia, bradycardia, or irregular rhythm changes acuity, ECG need, and treatment urgency.",
        "difficulty": "easy",
        "time_burden_minutes": 1,
        "equipment_needed": "watch/timer or bedside monitor",
        "patient_cooperation_required": "low",
        "limitations": "Heart rate is nonspecific and can reflect pain, fever, anxiety, medications, arrhythmia, hypovolemia, anemia, or endocrine state; interpret with rhythm, blood pressure, and context.",
        "likelihood_ratio_note": "Likelihood ratios are not applicable to routine bedside safety data; use this item to assess acuity, monitoring needs, and management safety rather than diagnostic probability.",
        "tags": [
          "adrenal_gland_disorders",
          "cushings_syndrome",
          "measure",
          "heart",
          "rate"
        ],
        "technique": "Palpate or monitor heart rate for a full interval, noting rate and regularity.",
        "rationale": "Screens severity and immediate safety findings that can change triage, monitoring, fluids, or urgent escalation for Cushing's Syndrome."
      },
      {
        "id": "safety_check_03",
        "label": "Measure orthostatic blood pressure",
        "item_type": "physical_exam_maneuver",
        "source": {
          "source_id": "ES_CUSHING_DX_2008",
          "source_section": "Cushing's Syndrome curated endocrine workup: basic bedside data and safety checks",
          "evidence_strength": "guideline/consensus",
          "version_date": "2008",
          "last_reviewed": "2026-06-06",
          "clinical_owner": "endocrine_content_review",
          "implementation_notes": "Guideline-backed endocrine workup content curated into the local knowledge schema; schema, source, PHI, and regression tests run on 2026-06-06."
        },
        "action": "Check and document as baseline bedside data for this workup. Orthostasis changes crisis concern, fluid strategy, and hormone replacement urgency.",
        "when_to_perform": "Perform when Cushing's Syndrome is the selected validated workup and the maneuver is clinically safe and relevant at bedside.",
        "findings_options": [
          "No orthostatic drop",
          "Orthostatic hypotension",
          "Symptomatic dizziness/presyncope",
          "Unable/unsafe to assess"
        ],
        "diagnostic_target": "hemodynamic safety, hypertension or hypotension severity, and medication or fluid-safety context",
        "LR_plus": "n/a",
        "LR_minus": "n/a",
        "management_change": "Orthostasis changes crisis concern, fluid strategy, and hormone replacement urgency.",
        "difficulty": "easy",
        "time_burden_minutes": 1,
        "equipment_needed": "blood pressure cuff",
        "patient_cooperation_required": "low",
        "limitations": "Single readings can be affected by cuff size, positioning, pain, anxiety, arrhythmia, recent activity, and medications; repeat or compare with baseline when results change management.",
        "likelihood_ratio_note": "Likelihood ratios are not applicable to routine bedside safety data; use this item to assess acuity, monitoring needs, and management safety rather than diagnostic probability.",
        "tags": [
          "adrenal_gland_disorders",
          "cushings_syndrome",
          "measure",
          "orthostatic",
          "blood",
          "pressure"
        ],
        "technique": "Measure supine or seated and standing blood pressure and heart rate to assess for an orthostatic drop.",
        "rationale": "Screens severity and immediate safety findings that can change triage, monitoring, fluids, or urgent escalation for Cushing's Syndrome."
      },
      {
        "id": "safety_check_04",
        "label": "Determine mental status",
        "item_type": "physical_exam_maneuver",
        "source": {
          "source_id": "ES_CUSHING_DX_2008",
          "source_section": "Cushing's Syndrome curated endocrine workup: basic bedside data and safety checks",
          "evidence_strength": "guideline/consensus",
          "version_date": "2008",
          "last_reviewed": "2026-06-06",
          "clinical_owner": "endocrine_content_review",
          "implementation_notes": "Guideline-backed endocrine workup content curated into the local knowledge schema; schema, source, PHI, and regression tests run on 2026-06-06."
        },
        "action": "Check and document as baseline bedside data for this workup. Altered mental status changes urgency, disposition, and need for monitored evaluation.",
        "when_to_perform": "Perform when Cushing's Syndrome is the selected validated workup and the maneuver is clinically safe and relevant at bedside.",
        "findings_options": [
          "Baseline/alert",
          "Confused",
          "Somnolent",
          "Agitated",
          "Unable to assess"
        ],
        "diagnostic_target": "encephalopathy, crisis severity, or airway-protection risk",
        "LR_plus": "n/a",
        "LR_minus": "n/a",
        "management_change": "Altered mental status changes urgency, disposition, and need for monitored evaluation.",
        "difficulty": "easy",
        "time_burden_minutes": 1,
        "equipment_needed": "none",
        "patient_cooperation_required": "low",
        "limitations": "Global appearance and perfusion are subjective and affected by baseline function, pain, medications, temperature, and examiner experience; pair with objective vitals and reassessment.",
        "likelihood_ratio_note": "Likelihood ratios are not applicable to routine bedside safety data; use this item to assess acuity, monitoring needs, and management safety rather than diagnostic probability.",
        "tags": [
          "adrenal_gland_disorders",
          "cushings_syndrome",
          "document",
          "mental"
        ],
        "when": {
          "termsAny": [
            "unstable",
            "confusion",
            "altered mental status",
            "severe",
            "crisis",
            "hypernatremia",
            "hyponatremia",
            "hypoglycemia",
            "hypercalcemia"
          ]
        },
        "technique": "Determine mental status using a brief bedside assessment of alertness, orientation, and responsiveness.",
        "rationale": "Screens severity and immediate safety findings that can change triage, monitoring, fluids, or urgent escalation for Cushing's Syndrome."
      }
    ],
    "conditionalExam": [
      {
        "id": "conditional_exam_01",
        "label": "Palpate abdomen for tenderness",
        "item_type": "physical_exam_maneuver",
        "source": {
          "source_id": "ES_CUSHING_DX_2008",
          "source_section": "Cushing's Syndrome curated endocrine workup: conditional bedside maneuver add-ons",
          "evidence_strength": "guideline/consensus",
          "version_date": "2008",
          "last_reviewed": "2026-06-06",
          "clinical_owner": "endocrine_content_review",
          "implementation_notes": "Guideline-backed endocrine workup content curated into the local knowledge schema; schema, source, PHI, and regression tests run on 2026-06-06."
        },
        "action": "Add when adrenal crisis, vomiting, abdominal pain, shock is present; this evaluates abdominal complication, endocrine crisis mimic, or precipitating illness. Tenderness changes adrenal crisis severity and mimic evaluation.",
        "rationale": "Targets abdominal complication, endocrine crisis mimic, or precipitating illness; positive, negative, or unable-to-assess findings guide escalation, diagnostic testing, treatment safety, or specialty planning for Cushing's Syndrome.",
        "technique": "Inspect and palpate the abdomen gently, localizing tenderness and stopping if guarding, rebound, or severe pain occurs.",
        "findings_options": [
          "Nontender",
          "Tender",
          "Guarding",
          "Rebound/peritoneal concern",
          "Unable to assess"
        ],
        "when_to_perform": "When adrenal crisis, vomiting, or abdominal pain is possible",
        "diagnostic_target": "abdominal complication, endocrine crisis mimic, or precipitating illness",
        "LR_plus": "n/a",
        "LR_minus": "n/a",
        "likelihood_ratio_note": "No maneuver-specific LR+/LR- is available in the local validated source metadata; treat this bedside finding as supportive and interpret it with the cited guideline, diagnostic tests, and patient context.",
        "management_change": "Tenderness changes adrenal crisis severity and mimic evaluation.",
        "difficulty": "easy",
        "time_burden_minutes": 1,
        "equipment_needed": "none",
        "patient_cooperation_required": "low",
        "limitations": "Palpate abdomen for tenderness is supportive for Cushing's Syndrome, not diagnostic by itself; reliability can be reduced by pain, positioning, acute illness, cooperation, body habitus, baseline disability, and examiner technique.",
        "tags": [
          "adrenal_gland_disorders",
          "cushings_syndrome",
          "palpate",
          "abdomen",
          "tenderness"
        ],
        "when": {
          "termsAny": [
            "adrenal crisis",
            "vomiting",
            "abdominal pain",
            "shock"
          ]
        }
      },
      {
        "id": "conditional_exam_02",
        "label": "Inspect mucous membranes for dehydration",
        "item_type": "physical_exam_maneuver",
        "source": {
          "source_id": "ES_CUSHING_DX_2008",
          "source_section": "Cushing's Syndrome curated endocrine workup: conditional bedside maneuver add-ons",
          "evidence_strength": "guideline/consensus",
          "version_date": "2008",
          "last_reviewed": "2026-06-06",
          "clinical_owner": "endocrine_content_review",
          "implementation_notes": "Guideline-backed endocrine workup content curated into the local knowledge schema; schema, source, PHI, and regression tests run on 2026-06-06."
        },
        "action": "Add when vomiting, dehydration, poor intake, polyuria, hyperglycemia is present; this evaluates volume status, dehydration severity, or peripheral perfusion. Dehydration changes fluid strategy, lab urgency, and monitoring needs.",
        "rationale": "Targets volume status, dehydration severity, or peripheral perfusion; positive, negative, or unable-to-assess findings guide escalation, diagnostic testing, treatment safety, or specialty planning for Cushing's Syndrome.",
        "technique": "Inspect oral mucosa and tongue moisture with attention to dry mucosa, cracked lips, and overall hydration context.",
        "findings_options": [
          "Moist",
          "Dry",
          "Very dry",
          "Unable to assess"
        ],
        "when_to_perform": "When vomiting, poor intake, polyuria, hyperglycemia, hypercalcemia, or hypernatremia is present",
        "diagnostic_target": "volume status, dehydration severity, or peripheral perfusion",
        "LR_plus": "n/a",
        "LR_minus": "n/a",
        "likelihood_ratio_note": "No maneuver-specific LR+/LR- is available in the local validated source metadata; treat this bedside finding as supportive and interpret it with the cited guideline, diagnostic tests, and patient context.",
        "management_change": "Dehydration changes fluid strategy, lab urgency, and monitoring needs.",
        "difficulty": "easy",
        "time_burden_minutes": 1,
        "equipment_needed": "none",
        "patient_cooperation_required": "low",
        "limitations": "Inspect mucous membranes for dehydration is supportive for Cushing's Syndrome, not diagnostic by itself; reliability can be reduced by pain, positioning, acute illness, cooperation, body habitus, baseline disability, and examiner technique.",
        "tags": [
          "adrenal_gland_disorders",
          "cushings_syndrome",
          "inspect",
          "mucous",
          "membranes",
          "dehydration"
        ],
        "when": {
          "termsAny": [
            "vomiting",
            "dehydration",
            "poor intake",
            "polyuria",
            "hyperglycemia",
            "hypercalcemia",
            "hypernatremia"
          ]
        }
      },
      {
        "id": "conditional_exam_03",
        "label": "Inspect and press lower leg edema",
        "item_type": "physical_exam_maneuver",
        "source": {
          "source_id": "ES_CUSHING_DX_2008",
          "source_section": "Cushing's Syndrome curated endocrine workup: conditional bedside maneuver add-ons",
          "evidence_strength": "guideline/consensus",
          "version_date": "2008",
          "last_reviewed": "2026-06-06",
          "clinical_owner": "endocrine_content_review",
          "implementation_notes": "Guideline-backed endocrine workup content curated into the local knowledge schema; schema, source, PHI, and regression tests run on 2026-06-06."
        },
        "action": "Add when edema, heart failure, kidney disease, vte is present; this evaluates volume overload, venous disease, or medication/renal-cardiac complication. Edema changes volume, VTE, renal-cardiac, and medication-safety interpretation.",
        "rationale": "Targets volume overload, venous disease, or medication/renal-cardiac complication; positive, negative, or unable-to-assess findings guide escalation, diagnostic testing, treatment safety, or specialty planning for Cushing's Syndrome.",
        "technique": "Inspect and press over both lower legs or dependent areas for pitting, symmetry, tenderness, and proximal extent.",
        "findings_options": [
          "None",
          "Trace",
          "1+",
          "2+",
          "3+",
          "4+",
          "Ankle or pedal",
          "Pretibial",
          "Sacral",
          "Unilateral",
          "Bilateral",
          "Unable to assess",
          "Other ___"
        ],
        "when_to_perform": "When severe Cushing syndrome, renal/cardiac disease, or medication effect could alter volume status",
        "diagnostic_target": "volume overload, venous disease, or medication/renal-cardiac complication",
        "LR_plus": "n/a",
        "LR_minus": "n/a",
        "likelihood_ratio_note": "No maneuver-specific LR+/LR- is available in the local validated source metadata; treat this bedside finding as supportive and interpret it with the cited guideline, diagnostic tests, and patient context.",
        "management_change": "Edema changes volume, VTE, renal-cardiac, and medication-safety interpretation.",
        "difficulty": "easy",
        "time_burden_minutes": 1,
        "equipment_needed": "none",
        "patient_cooperation_required": "low",
        "limitations": "Inspect and press lower leg edema is supportive for Cushing's Syndrome, not diagnostic by itself; reliability can be reduced by pain, positioning, acute illness, cooperation, body habitus, baseline disability, and examiner technique.",
        "tags": [
          "adrenal_gland_disorders",
          "cushings_syndrome",
          "inspect",
          "press",
          "lower",
          "edema"
        ],
        "when": {
          "termsAny": [
            "edema",
            "heart failure",
            "kidney disease",
            "vte"
          ]
        }
      }
    ],
    "endocrine_metadata": {
      "generated_from": "scripts/generate-endocrine-workups.js",
      "source_diagnosis": "Cushing's Syndrome",
      "category": "Adrenal Gland Disorders",
      "aliases": [],
      "source_ids": [
        "ES_CUSHING_DX_2008",
        "ES_CUSHING_TREATMENT_2015",
        "ESE_ADRENAL_INCIDENTALOMA_2023"
      ],
      "reference_values": [
        "DST, late-night salivary cortisol, and UFC cutoffs are assay-specific; abnormal screening generally needs confirmation.",
        "Use local laboratory intervals and assay-specific cutoffs; endocrine immunoassays are affected by pregnancy, age, sex, acute illness, binding proteins, biotin, and medication effects."
      ],
      "decision_steps": [
        "Exclude exogenous glucocorticoid exposure first, including injections, creams, inhaled, topical, supplements, and medication interactions.",
        "Screen with one of the recommended first-line tests: 1-mg overnight dexamethasone suppression, late-night salivary cortisol, or 24-hour urinary free cortisol, repeating or confirming abnormal results.",
        "After endogenous hypercortisolism is confirmed, measure ACTH to separate ACTH-independent from ACTH-dependent disease.",
        "Use adrenal imaging for ACTH-independent disease; for ACTH-dependent disease use pituitary MRI and inferior petrosal sinus sampling when imaging and biochemistry are discordant.",
        "Confirm that Cushing's Syndrome is the selected clinical intent, then screen for red flags before routine outpatient testing.",
        "Order the first-line tests in sequence: Exclude exogenous steroids; 1-mg overnight DST: cortisol >1.8 ug/dL abnormal/sensitive cutoff; Late-night salivary cortisol, often two samples.",
        "Interpret numeric results against the workup cutoffs and local assay ranges: DST, late-night salivary cortisol, and UFC cutoffs are assay-specific; abnormal screening generally needs confirmation.",
        "If the initial result is equivocal, discordant with the phenotype, or affected by medication, acute illness, pregnancy, age, sex, or assay interference, repeat or confirm using the next guideline test before committing to long-term therapy."
      ],
      "treatment_options": [
        "Treat the cause when feasible: transsphenoidal pituitary surgery for Cushing disease, adrenalectomy for unilateral adrenal cortisol excess, or ectopic source-directed therapy.",
        "Control severe hypercortisolism complications urgently, including infection, VTE, psychosis, hypokalemia, hypertension, diabetes, and heart failure.",
        "Use steroidogenesis inhibitors, glucocorticoid receptor blockade, pituitary-directed drugs, radiation, or bilateral adrenalectomy when surgery is delayed, incomplete, impossible, or recurrent.",
        "Provide postoperative adrenal insufficiency monitoring, glucocorticoid replacement/taper, recurrence surveillance, and cardiometabolic/bone risk treatment.",
        "Treat unstable presentations first using the urgent escalation rule for Cushing's Syndrome; draw time-sensitive labs only if doing so does not delay stabilization.",
        "For confirmed Cushing's Syndrome, choose therapy based on severity, comorbidities, pregnancy/fertility context, contraindications, patient preference, and local specialty pathway.",
        "Monitor treatment response with the condition-specific clinical endpoint plus the most relevant labs or imaging listed in this workup.",
        "Escalate to endocrinology or the relevant specialty when results are severe, discordant, recurrent, treatment-limiting, or require localization, surgery, genetic testing, or high-risk medication."
      ],
      "quality_issues": [],
      "activation_status": "active_guideline_workup"
    },
    "clinical_cutoff_review": {
      "status": "source_backed_cutoff_enrichment_added",
      "reviewed_on": "2026-06-11",
      "review_note": "Cutoff rows were added because the prior module evidence did not expose enough explicit guideline thresholds for pathway traversal."
    }
  }
}
